start_app_mai/__init__.py
start_app_mai/cli.py
start_app_mai-0.2.2.dist-info/METADATA
start_app_mai-0.2.2.dist-info/WHEEL
start_app_mai-0.2.2.dist-info/entry_points.txt
start_app_mai-0.2.2.dist-info/top_level.txt
start_app_mai-0.2.2.dist-info/RECORD
