Metadata-Version: 2.4
Name: start_app_mai
Version: 0.2.2
Summary: Générateur de structure d'app Django personnalisée
Author: soro F M
Author-email: soferelaha@gmail.com
License: MIT
Classifier: Programming Language :: Python :: 3
Classifier: Framework :: Django
Classifier: License :: OSI Approved :: MIT License
Dynamic: author
Dynamic: author-email
Dynamic: classifier
Dynamic: description
Dynamic: description-content-type
Dynamic: license
Dynamic: summary
